[
    {
        "title": "Native Americans for kids: Cherokee, Apache, Navajo, Iroquois and Sioux",
        "category": "Anthropology",
        "questions-average-bleu": 0.7081340712301277,
        "options-average-bleu": 0.08280275473428753,
        "multiple-choice": [
            {
                "question_bleu": 0.6917017543042558,
                "options_bleu": [
                    0.09534061816653486,
                    0.1109916805067346,
                    0.03461237989415256,
                    0.10352789809557715
                ]
            },
            {
                "question_bleu": 0.6838911999336902,
                "options_bleu": [
                    0.0271849428088456,
                    0.0007251930352960707,
                    0.008242894079861797,
                    0.10081042988795336
                ]
            },
            {
                "question_bleu": 0.7299795676982808,
                "options_bleu": [
                    0.010011924518188053,
                    0.0026285583503802795,
                    0.0020904155149136417,
                    0.0009118819655545162
                ]
            },
            {
                "question_bleu": 0.7400828044922853,
                "options_bleu": [
                    0.010011924518188053,
                    0.0009118819655545162,
                    0.0034593773364647584,
                    0.016285161758772083
                ]
            },
            {
                "question_bleu": 0.6950150297221263,
                "options_bleu": [
                    0.2958386563484154,
                    0.33719746371087733,
                    0.1430389394293773,
                    0.3522328727941088
                ]
            }
        ]
    },
    {
        "title": "Why does everyone hate pigeons?",
        "category": "Science & Technology",
        "questions-average-bleu": 0.7327141729922679,
        "options-average-bleu": 0.2708529481726544,
        "multiple-choice": [
            {
                "question_bleu": 0.6893409630302637,
                "options_bleu": [
                    0.5819513908908385,
                    0.2853940203175198,
                    0.13319060307857306,
                    0.2291605604289243
                ]
            },
            {
                "question_bleu": 0.7447819789879647,
                "options_bleu": [
                    0.12863390296381264,
                    0.5311766362354581,
                    0.260606021180331,
                    0.1486146494215455
                ]
            },
            {
                "question_bleu": 0.7299795676982808,
                "options_bleu": [
                    0.1626960223497547,
                    0.28216115881718296,
                    0.30001714530654233,
                    0.28018095817810484
                ]
            },
            {
                "question_bleu": 0.7517939646342201,
                "options_bleu": [
                    0.19645230986529175,
                    0.2747586308195736,
                    0.5685331719237912,
                    0.34641697401065913
                ]
            },
            {
                "question_bleu": 0.7476743906106103,
                "options_bleu": [
                    0.15131273914544516,
                    0.142496898647282,
                    0.17955889891575613,
                    0.23374627095669945
                ]
            }
        ]
    },
    {
        "title": "What it's like to be a Muslim in America - Dalia Mogahed",
        "category": "Religion",
        "questions-average-bleu": 0.7236178046990547,
        "options-average-bleu": 1.0,
        "multiple-choice": [
            {
                "question_bleu": 0.7539221180326289,
                "options_bleu": [
                    1.0,
                    1.0,
                    1.0,
                    1.0
                ]
            },
            {
                "question_bleu": 0.7002959704822554,
                "options_bleu": [
                    1.0,
                    1.0,
                    1.0,
                    1.0
                ]
            },
            {
                "question_bleu": 0.6912065848593708,
                "options_bleu": [
                    1.0,
                    1.0,
                    1.0,
                    1.0
                ]
            },
            {
                "question_bleu": 0.7860753021519787,
                "options_bleu": [
                    1.0,
                    1.0,
                    1.0,
                    1.0
                ]
            },
            {
                "question_bleu": 0.6865890479690392,
                "options_bleu": [
                    1.0,
                    1.0,
                    1.0,
                    1.0
                ]
            }
        ]
    },
    {
        "title": "Is it normal to talk to yourself?",
        "category": "Psychology",
        "questions-average-bleu": 0.7138053337400903,
        "options-average-bleu": 0.367200326941718,
        "multiple-choice": [
            {
                "question_bleu": 0.633160218956179,
                "options_bleu": [
                    0.42162833686950796,
                    0.7896895367562644,
                    0.3072569999303029,
                    0.2872406602706351
                ]
            },
            {
                "question_bleu": 0.7670387248467655,
                "options_bleu": [
                    0.2249401292045871,
                    0.5647091305013939,
                    0.5418580162342823,
                    0.22179246333978123
                ]
            },
            {
                "question_bleu": 0.7090414279406884,
                "options_bleu": [
                    0.6781836812426999,
                    0.28561430670807897,
                    0.12240299967308946,
                    0.3026114824310638
                ]
            },
            {
                "question_bleu": 0.7323591444439925,
                "options_bleu": [
                    0.4250900852537615,
                    0.43927354375945515,
                    0.16816764188435615,
                    0.2918952972702044
                ]
            },
            {
                "question_bleu": 0.727427152512826,
                "options_bleu": [
                    0.2251908119091223,
                    0.3419000790410779,
                    0.3688340732601691,
                    0.33572726329452635
                ]
            }
        ]
    },
    {
        "title": "How tall can a tree grow? - Valentin Hammoudi",
        "category": "Science & Technology",
        "questions-average-bleu": 0.70796692640566,
        "options-average-bleu": 0.48394252328255316,
        "multiple-choice": [
            {
                "question_bleu": 0.6798237988565304,
                "options_bleu": [
                    0.4482700320176827,
                    0.846481724890614,
                    0.7311104457090247,
                    0.4482700320176827
                ]
            },
            {
                "question_bleu": 0.6733792440977188,
                "options_bleu": [
                    0.5516251532744788,
                    0.2117926589889878,
                    0.3348946563001698,
                    0.23036426554284148
                ]
            },
            {
                "question_bleu": 0.7203294535577252,
                "options_bleu": [
                    0.345720784641941,
                    0.7348889200874658,
                    0.3829453159673758,
                    0.4384209576532837
                ]
            },
            {
                "question_bleu": 0.7568500260087727,
                "options_bleu": [
                    0.7311104457090247,
                    0.7952707287670506,
                    0.3839817133079349,
                    0.3858594304868543
                ]
            },
            {
                "question_bleu": 0.7094521095075528,
                "options_bleu": [
                    0.5623413251903491,
                    0.24334661539897845,
                    0.5318295896944989,
                    0.3403256700048232
                ]
            }
        ]
    },
    {
        "title": "Can you solve the dark matter fuel riddle? - Daniel Finkel",
        "category": "Literature & Language",
        "questions-average-bleu": 0.7331491045830874,
        "options-average-bleu": 0.20712811911068396,
        "multiple-choice": [
            {
                "question_bleu": 0.7295825158420239,
                "options_bleu": [
                    0.4617366309441026,
                    0.2249401292045871,
                    0.18662592048643376,
                    0.36882702940104417
                ]
            },
            {
                "question_bleu": 0.7565391407404769,
                "options_bleu": [
                    0.291244316565298,
                    0.4751597949671373,
                    0.2871149682829062,
                    0.2850982895931448
                ]
            },
            {
                "question_bleu": 0.7192399680297693,
                "options_bleu": [
                    0.15813859795767055,
                    0.1787537033869555,
                    0.1506914981676572,
                    0.1983211647113318
                ]
            },
            {
                "question_bleu": 0.7510499815709779,
                "options_bleu": [
                    0.00012340980408667956,
                    0.01831563888873418,
                    0.01831563888873418,
                    0.01831563888873418
                ]
            },
            {
                "question_bleu": 0.7093339167321887,
                "options_bleu": [
                    0.08842343588102626,
                    0.12895564188125258,
                    0.12895564188125258,
                    0.47450529243159106
                ]
            }
        ]
    },
    {
        "title": "Why should you read Toni Morrison's \"Beloved\"? - Yen Pham",
        "category": "Literature",
        "questions-average-bleu": 0.742303275497739,
        "options-average-bleu": 0.32960946210940956,
        "multiple-choice": [
            {
                "question_bleu": 0.7364279629037999,
                "options_bleu": [
                    0.3968244753595938,
                    0.4117731803000629,
                    0.516695656246484,
                    0.24454418420017768
                ]
            },
            {
                "question_bleu": 0.786671944177035,
                "options_bleu": [
                    0.2767927940848509,
                    0.25395822235046633,
                    0.48023219270642,
                    0.27508320873851433
                ]
            },
            {
                "question_bleu": 0.8178362024635121,
                "options_bleu": [
                    0.19265501759915832,
                    0.15410872428072994,
                    0.23961905428739735,
                    0.41567628215354646
                ]
            },
            {
                "question_bleu": 0.624953384615582,
                "options_bleu": [
                    0.3019754926876866,
                    0.09212404327949333,
                    0.2872316105853658,
                    0.3472515275583214
                ]
            },
            {
                "question_bleu": 0.745626883328766,
                "options_bleu": [
                    0.526537094641459,
                    0.42443394424895264,
                    0.4936725010709589,
                    0.2610000358085522
                ]
            }
        ]
    },
    {
        "title": "Can you outsmart this logical fallacy? - Alex Gendler",
        "category": "Thinking & Learning",
        "questions-average-bleu": 0.7402900649968045,
        "options-average-bleu": 0.2758729642703561,
        "multiple-choice": [
            {
                "question_bleu": 0.7400828044922853,
                "options_bleu": [
                    0.2537689151092334,
                    0.5395472684295519,
                    0.220364809176831,
                    0.20831209164594536
                ]
            },
            {
                "question_bleu": 0.7142622297615925,
                "options_bleu": [
                    0.27633183772849373,
                    0.4709207802660357,
                    0.12641784775928847,
                    0.2736355949650343
                ]
            },
            {
                "question_bleu": 0.8537382425870722,
                "options_bleu": [
                    0.23457017814085346,
                    0.265816558562709,
                    0.2016641525118275,
                    0.15211292552332176
                ]
            },
            {
                "question_bleu": 0.6610079036990795,
                "options_bleu": [
                    0.2148007607373683,
                    0.3011785378475463,
                    0.2737208605063196,
                    0.17721345337870106
                ]
            },
            {
                "question_bleu": 0.7323591444439925,
                "options_bleu": [
                    0.44403395204273166,
                    0.40653583053190523,
                    0.2488172594795415,
                    0.22769567106388294
                ]
            }
        ]
    },
    {
        "title": "Einstein's twin paradox explained - Amber Stuver",
        "category": "Mathematics",
        "questions-average-bleu": 0,
        "options-average-bleu": 0,
        "multiple-choice": []
    },
    {
        "title": "Why should you wear sunscreen?",
        "category": "Science & Technology",
        "questions-average-bleu": 0.7748273732326526,
        "options-average-bleu": 0.2895210544822536,
        "multiple-choice": [
            {
                "question_bleu": 0.7521206186172787,
                "options_bleu": [
                    0.5053483543335474,
                    0.5659119256652702,
                    0.5828233954152654,
                    0.5734090813814468
                ]
            },
            {
                "question_bleu": 0.7633947323726819,
                "options_bleu": [
                    0.14874232609060656,
                    0.26073367938153846,
                    0.12142365144989464,
                    0.11038809613846576
                ]
            },
            {
                "question_bleu": 0.745626883328766,
                "options_bleu": [
                    0.5035337887555859,
                    0.28604120762397683,
                    0.21576146358278564,
                    0.43027073778533753
                ]
            },
            {
                "question_bleu": 0.7259795291154771,
                "options_bleu": [
                    0.17462730519646974,
                    0.2535014508969077,
                    0.05315170260104859,
                    0.22379058217161163
                ]
            },
            {
                "question_bleu": 0.887015102729059,
                "options_bleu": [
                    0.18999392312155455,
                    0.29055697010285314,
                    0.2226928403118228,
                    0.07771860763908515
                ]
            }
        ]
    },
    {
        "title": "The surprisingly long history of electric cars - Daniel Sperling and Gil Tal",
        "category": "Design, Engineering & Technology",
        "questions-average-bleu": 0.6701730398223786,
        "options-average-bleu": 0.28817473633702423,
        "multiple-choice": [
            {
                "question_bleu": 0.7009305846091448,
                "options_bleu": [
                    0.21554491059608466,
                    0.516534483087896,
                    0.39707253867809,
                    0.1722578424209436
                ]
            },
            {
                "question_bleu": 0.6416334504967062,
                "options_bleu": [
                    0.04076220397836621,
                    0.04076220397836621,
                    0.4963786070388903,
                    0.04076220397836621
                ]
            },
            {
                "question_bleu": 0.6434588841607617,
                "options_bleu": [
                    0.3033411650002924,
                    0.5420488449365982,
                    0.31642571776698514,
                    0.3805081932743349
                ]
            },
            {
                "question_bleu": 0.6672290177922376,
                "options_bleu": [
                    0.44871685567204544,
                    0.3352113419081665,
                    0.43100828948539904,
                    0.46838203129298117
                ]
            },
            {
                "question_bleu": 0.697613262053043,
                "options_bleu": [
                    0.3771661792221777,
                    0.05351964983159561,
                    0.10004556682026908,
                    0.0870458977726377
                ]
            }
        ]
    },
    {
        "title": "Food waste causes climate change. Here's how we stop it",
        "category": "Science & Technology",
        "questions-average-bleu": 0.7245908525988989,
        "options-average-bleu": 1.0,
        "multiple-choice": [
            {
                "question_bleu": 0.6627953568839928,
                "options_bleu": [
                    1.0,
                    1.0,
                    1.0,
                    1.0
                ]
            },
            {
                "question_bleu": 0.7837698111269349,
                "options_bleu": [
                    1.0,
                    1.0,
                    1.0,
                    1.0
                ]
            },
            {
                "question_bleu": 0.7730551756939454,
                "options_bleu": [
                    1.0,
                    1.0,
                    1.0,
                    1.0
                ]
            },
            {
                "question_bleu": 0.6985342056580097,
                "options_bleu": [
                    1.0,
                    1.0,
                    1.0,
                    1.0
                ]
            },
            {
                "question_bleu": 0.7047997136316118,
                "options_bleu": [
                    1.0,
                    1.0,
                    1.0,
                    1.0
                ]
            }
        ]
    },
    {
        "title": "How do self-driving cars \"see\"? - Sajan Saini",
        "category": "Design, Engineering & Technology",
        "questions-average-bleu": 0.7035400943961856,
        "options-average-bleu": 0.22261551995259582,
        "multiple-choice": [
            {
                "question_bleu": 0.6660917764903399,
                "options_bleu": [
                    0.008984566060869,
                    0.11411797198557871,
                    0.06417325159440547,
                    0.11411797198557871
                ]
            },
            {
                "question_bleu": 0.7206183364926947,
                "options_bleu": [
                    0.15380549797850745,
                    0.27742078013901367,
                    0.27171508006316425,
                    0.2678360274625165
                ]
            },
            {
                "question_bleu": 0.7132650412498627,
                "options_bleu": [
                    0.0026645864651897886,
                    0.0026645864651897886,
                    0.0030275547453758153,
                    3.2530471172671234e-05
                ]
            },
            {
                "question_bleu": 0.6784447722174308,
                "options_bleu": [
                    0.4989714759382384,
                    0.32807824887287756,
                    0.628622291663189,
                    0.483558053397863
                ]
            },
            {
                "question_bleu": 0.7392805455305997,
                "options_bleu": [
                    0.37994673868264234,
                    0.42968211230321307,
                    0.21389310374289533,
                    0.2089979690344356
                ]
            }
        ]
    },
    {
        "title": "Why is meningitis so dangerous? - Melvin Sanicas",
        "category": "Health",
        "questions-average-bleu": 0.7286245593598011,
        "options-average-bleu": 0.4624877123949491,
        "multiple-choice": [
            {
                "question_bleu": 0.6964705665515708,
                "options_bleu": [
                    0.37700638045494705,
                    0.2602844061600252,
                    0.7447819789879647,
                    0.473369877285295
                ]
            },
            {
                "question_bleu": 0.727427152512826,
                "options_bleu": [
                    0.20189651799465538,
                    0.6511126026643229,
                    0.20687381245863395,
                    0.11380295453101374
                ]
            },
            {
                "question_bleu": 0.746089766252147,
                "options_bleu": [
                    0.3087818953963449,
                    0.36921489043401184,
                    0.3582426406556729,
                    1.0
                ]
            },
            {
                "question_bleu": 0.7701759630121805,
                "options_bleu": [
                    0.31007120066002053,
                    0.4134083367482478,
                    0.7140741917751113,
                    0.3829453159673758
                ]
            },
            {
                "question_bleu": 0.7029593484702812,
                "options_bleu": [
                    0.8139957963337889,
                    0.6887246539984299,
                    0.4380489412320636,
                    0.42311785416105785
                ]
            }
        ]
    },
    {
        "title": "What is phantom traffic and why is it ruining your life? - Benjamin Seibold",
        "category": "Design, Engineering & Technology",
        "questions-average-bleu": 0.7350570701255201,
        "options-average-bleu": 0.344271829598357,
        "multiple-choice": [
            {
                "question_bleu": 0.7745966692414834,
                "options_bleu": [
                    0.299597896427608,
                    0.3005046148503396,
                    0.5158614620834666,
                    0.3021646635659734
                ]
            },
            {
                "question_bleu": 0.7093339167321887,
                "options_bleu": [
                    0.30734791080992024,
                    0.3584847750783843,
                    0.40420195162193784,
                    0.25396171108773413
                ]
            },
            {
                "question_bleu": 0.7006287845027608,
                "options_bleu": [
                    0.27066208676801745,
                    0.4852745724436496,
                    0.4153016723546559,
                    0.23390126244968992
                ]
            },
            {
                "question_bleu": 0.7250224017489714,
                "options_bleu": [
                    0.3385771445710467,
                    0.17200819168819473,
                    0.30531202287569587,
                    0.2495766672598366
                ]
            },
            {
                "question_bleu": 0.7657035784021965,
                "options_bleu": [
                    0.34133611822819543,
                    0.3356448038491994,
                    0.45518551547988323,
                    0.5405315484737119
                ]
            }
        ]
    },
    {
        "title": "The race to decode a mysterious language - Susan Lupack",
        "category": "Linguistics",
        "questions-average-bleu": 0.7417600893382146,
        "options-average-bleu": 0.47845829160977926,
        "multiple-choice": [
            {
                "question_bleu": 0.7270447990811325,
                "options_bleu": [
                    1.0,
                    0.8265168183793802,
                    0.722160038719837,
                    0.816496580927726
                ]
            },
            {
                "question_bleu": 0.7427498127683173,
                "options_bleu": [
                    0.11514001562249686,
                    0.2924720367433956,
                    0.3245772231556433,
                    0.27900556033116075
                ]
            },
            {
                "question_bleu": 0.7875110621102679,
                "options_bleu": [
                    0.22717899280914527,
                    0.2814459156536722,
                    0.5647091305013939,
                    0.3323123922980402
                ]
            },
            {
                "question_bleu": 0.7295825158420239,
                "options_bleu": [
                    0.48217764100758403,
                    0.668740304976422,
                    0.7146704964214272,
                    0.6580370064762462
                ]
            },
            {
                "question_bleu": 0.7219122568893311,
                "options_bleu": [
                    0.32742442913833936,
                    0.24767920147203748,
                    0.3760342788692612,
                    0.3123877686923767
                ]
            }
        ]
    },
    {
        "title": "What if all the ice melted on Earth?",
        "category": "Science & Technology",
        "questions-average-bleu": 0.7094828060654262,
        "options-average-bleu": 0.5649920504431926,
        "multiple-choice": [
            {
                "question_bleu": 0.7162326270441588,
                "options_bleu": [
                    0.37991784282579627,
                    0.3495274586585512,
                    0.32201734343516736,
                    0.32743129582216096
                ]
            },
            {
                "question_bleu": 0.6768477282896436,
                "options_bleu": [
                    0.3639412530979476,
                    0.3706218611316513,
                    0.36889397323344053,
                    0.3819227559309534
                ]
            },
            {
                "question_bleu": 0.6980972118841674,
                "options_bleu": [
                    0.7707713836060629,
                    0.8408964152537145,
                    0.423013599415148,
                    0.40228686126014285
                ]
            },
            {
                "question_bleu": 0.7685209321928833,
                "options_bleu": [
                    1.0,
                    1.0,
                    1.0,
                    1.0
                ]
            },
            {
                "question_bleu": 0.6877155309162784,
                "options_bleu": [
                    0.7732122568400192,
                    0.35571061935176884,
                    0.3771970284958751,
                    0.4924790605054523
                ]
            }
        ]
    },
    {
        "title": "Why are you always tired?",
        "category": "Health",
        "questions-average-bleu": 0.7171632823809073,
        "options-average-bleu": 0.7192193896418242,
        "multiple-choice": [
            {
                "question_bleu": 0.7400828044922853,
                "options_bleu": [
                    0.5533409598501607,
                    0.5533409598501607,
                    0.5671276403520978,
                    0.5695988432761473
                ]
            },
            {
                "question_bleu": 0.748406329216425,
                "options_bleu": [
                    1.0,
                    1.0,
                    1.0,
                    1.0
                ]
            },
            {
                "question_bleu": 0.6985342056580097,
                "options_bleu": [
                    0.7226568811456053,
                    0.5491004867761125,
                    0.8801117367933934,
                    0.7598356856515925
                ]
            },
            {
                "question_bleu": 0.6893409630302637,
                "options_bleu": [
                    0.5946035575013605,
                    0.5555238068023582,
                    0.6481388934544839,
                    0.6529942057256104
                ]
            },
            {
                "question_bleu": 0.7094521095075528,
                "options_bleu": [
                    1.0,
                    0.5577503997480662,
                    0.6481388934544839,
                    0.5721248424548514
                ]
            }
        ]
    },
    {
        "title": "The life, legacy & assassination of an African revolutionary - Lisa Janae Bacon",
        "category": "History",
        "questions-average-bleu": 0.7364833149785186,
        "options-average-bleu": 0.6656039750826392,
        "multiple-choice": [
            {
                "question_bleu": 0.7299795676982808,
                "options_bleu": [
                    0.668740304976422,
                    0.6865890479690392,
                    0.7598356856515925,
                    0.7311104457090247
                ]
            },
            {
                "question_bleu": 0.7476743906106103,
                "options_bleu": [
                    1.0,
                    1.0,
                    1.0,
                    1.0
                ]
            },
            {
                "question_bleu": 0.7311104457090247,
                "options_bleu": [
                    0.6559965570884768,
                    0.6389431042462724,
                    0.28533728885279996,
                    0.5814307369682193
                ]
            },
            {
                "question_bleu": 0.7254204378043243,
                "options_bleu": [
                    0.6718150541065748,
                    0.30684759595658995,
                    0.31012985529573606,
                    0.6955425557411256
                ]
            },
            {
                "question_bleu": 0.7482317330703532,
                "options_bleu": [
                    0.5983790078367693,
                    0.7529586373193689,
                    0.6094183098284,
                    0.35900531410637465
                ]
            }
        ]
    },
    {
        "title": "I Like Myself - Children's books read aloud",
        "category": "Literature",
        "questions-average-bleu": 0.7702981600281531,
        "options-average-bleu": 0.6442774019821296,
        "multiple-choice": [
            {
                "question_bleu": 0.7707713836060629,
                "options_bleu": [
                    0.6803749333171202,
                    0.7909129169328468,
                    0.7016879391277372,
                    0.7952707287670506
                ]
            },
            {
                "question_bleu": 0.7755106492019573,
                "options_bleu": [
                    0.5946035575013605,
                    0.6293321993912832,
                    0.668740304976422,
                    0.2822052107603345
                ]
            },
            {
                "question_bleu": 0.7419446627365011,
                "options_bleu": [
                    0.6595140909797456,
                    0.6063062848485936,
                    0.5533409598501607,
                    0.7009305846091448
                ]
            },
            {
                "question_bleu": 0.8034284189446518,
                "options_bleu": [
                    0.6500593260343692,
                    0.7311104457090247,
                    0.6042750794713536,
                    0.7259795291154771
                ]
            },
            {
                "question_bleu": 0.7598356856515925,
                "options_bleu": [
                    0.6238986072117501,
                    0.5336172773868456,
                    0.6640471006217092,
                    0.6893409630302637
                ]
            }
        ]
    },
    {
        "title": "What is schizophrenia? - Anees Bahji",
        "category": "Health",
        "questions-average-bleu": 0.6892430649394313,
        "options-average-bleu": 0.5171772091888296,
        "multiple-choice": [
            {
                "question_bleu": 0.6856838527934191,
                "options_bleu": [
                    0.7203294535577252,
                    0.6481388934544839,
                    0.3722584895657008,
                    0.6389431042462724
                ]
            },
            {
                "question_bleu": 0.716729493542774,
                "options_bleu": [
                    0.8633400213704505,
                    0.4841524713034601,
                    0.7691605673134586,
                    0.7311104457090247
                ]
            },
            {
                "question_bleu": 0.6553587376109387,
                "options_bleu": [
                    0.2621576039711584,
                    0.2655009184259522,
                    0.32303524793448585,
                    0.3114711062274207
                ]
            },
            {
                "question_bleu": 0.7243961401283154,
                "options_bleu": [
                    0.24085666922784627,
                    0.5925566990494595,
                    0.26185719316840583,
                    0.33265096878635064
                ]
            },
            {
                "question_bleu": 0.6640471006217092,
                "options_bleu": [
                    0.7476743906106103,
                    0.7400828044922853,
                    0.34780982703458335,
                    0.6904573083274563
                ]
            }
        ]
    },
    {
        "title": "How do pelicans survive their death-defying dives?",
        "category": "Environmental Science",
        "questions-average-bleu": 0.6920566564793326,
        "options-average-bleu": 0.16282934757235162,
        "multiple-choice": [
            {
                "question_bleu": 0.6669919493526925,
                "options_bleu": [
                    0.009795678625726646,
                    0.04842614075499488,
                    0.08315860835576719,
                    0.13286144207035225
                ]
            },
            {
                "question_bleu": 0.670422683816333,
                "options_bleu": [
                    0.06992777566385222,
                    0.1527776037370602,
                    0.04842614075499488,
                    0.13286144207035225
                ]
            },
            {
                "question_bleu": 0.6828267746069693,
                "options_bleu": [
                    0.32774568052975916,
                    0.32774568052975916,
                    0.3521856535823236,
                    0.32774568052975916
                ]
            },
            {
                "question_bleu": 0.7419446627365011,
                "options_bleu": [
                    0.12364007630744668,
                    0.2623803576081212,
                    0.21960557027924005,
                    0.23331045782126386
                ]
            },
            {
                "question_bleu": 0.6980972118841674,
                "options_bleu": [
                    0.13286144207035225,
                    0.04842614075499488,
                    0.06992777566385222,
                    0.1527776037370602
                ]
            }
        ]
    },
    {
        "title": "The truth about electroconvulsive therapy (ECT) - Helen M. Farrell",
        "category": "Health",
        "questions-average-bleu": 0.764169340010976,
        "options-average-bleu": 0.37899117000273697,
        "multiple-choice": [
            {
                "question_bleu": 0.7718052844994459,
                "options_bleu": [
                    0.17377394345044514,
                    0.17377394345044514,
                    0.17377394345044514,
                    0.17377394345044514
                ]
            },
            {
                "question_bleu": 0.8076682939508287,
                "options_bleu": [
                    0.4035278637463991,
                    0.6389431042462724,
                    0.34709247204129007,
                    0.33197553186281176
                ]
            },
            {
                "question_bleu": 0.7029593484702812,
                "options_bleu": [
                    0.2581988897471612,
                    0.37074683901524685,
                    0.36145686726468856,
                    0.3538995029906511
                ]
            },
            {
                "question_bleu": 0.7536324264832723,
                "options_bleu": [
                    0.4256279541919936,
                    0.27768352844338134,
                    0.4784023976826744,
                    0.785629301801026
                ]
            },
            {
                "question_bleu": 0.7847813466510527,
                "options_bleu": [
                    0.6606328636027614,
                    0.27694132751313416,
                    0.5977414160866288,
                    0.3162277660168379
                ]
            }
        ]
    },
    {
        "title": "What is imposter syndrome and how can you combat it? - Elizabeth Cox",
        "category": "Psychology",
        "questions-average-bleu": 0.7198193591684401,
        "options-average-bleu": 0.4325640198563871,
        "multiple-choice": [
            {
                "question_bleu": 0.7006287845027608,
                "options_bleu": [
                    0.33840754551690133,
                    0.6419358938757569,
                    0.2530618805649334,
                    0.6068194518630144
                ]
            },
            {
                "question_bleu": 0.7364279629037999,
                "options_bleu": [
                    0.303249234086981,
                    0.29843512188579213,
                    0.31337076923330476,
                    0.668740304976422
                ]
            },
            {
                "question_bleu": 0.7278825061958952,
                "options_bleu": [
                    0.5831124749964698,
                    0.3966407007413138,
                    0.4027672046365773,
                    0.6530443861294963
                ]
            },
            {
                "question_bleu": 0.6930977286178779,
                "options_bleu": [
                    0.5146906560381768,
                    0.22654234028691125,
                    0.2448907692553361,
                    0.5012373629798178
                ]
            },
            {
                "question_bleu": 0.7410598136218668,
                "options_bleu": [
                    0.35555433856217356,
                    0.22562819232542763,
                    0.5797718591890967,
                    0.5433799099838407
                ]
            }
        ]
    },
    {
        "title": "Fabulous food chains",
        "category": "Environmental Science",
        "questions-average-bleu": 0.7625067994908086,
        "options-average-bleu": 0.3719735528970144,
        "multiple-choice": [
            {
                "question_bleu": 0.8408964152537145,
                "options_bleu": [
                    0.35930411196308426,
                    0.6025510245872937,
                    0.21850749656691937,
                    0.38499720887869576
                ]
            },
            {
                "question_bleu": 0.7093339167321887,
                "options_bleu": [
                    0.2822651961477009,
                    0.45006882054160513,
                    0.2822651961477009,
                    0.4175768018258731
                ]
            },
            {
                "question_bleu": 0.7565391407404769,
                "options_bleu": [
                    0.07984193542788678,
                    0.03260509236999754,
                    0.09852859740626556,
                    0.1344423053500887
                ]
            },
            {
                "question_bleu": 0.8153072164002068,
                "options_bleu": [
                    0.23446055125848833,
                    0.5236451551896005,
                    0.2304677152768091,
                    0.24493390281390082
                ]
            },
            {
                "question_bleu": 0.6904573083274563,
                "options_bleu": [
                    0.5506953149031838,
                    0.7825422900366437,
                    0.7896895367562644,
                    0.7400828044922853
                ]
            }
        ]
    },
    {
        "title": "How An Igloo Keeps You Warm",
        "category": "Design, Engineering & Technology",
        "questions-average-bleu": 0.7337802445472571,
        "options-average-bleu": 0.2678584858991483,
        "multiple-choice": [
            {
                "question_bleu": 0.6959325433099479,
                "options_bleu": [
                    0.4201233638773121,
                    0.33403730481326194,
                    0.4201233638773121,
                    0.33403730481326194
                ]
            },
            {
                "question_bleu": 0.7663029554391028,
                "options_bleu": [
                    0.29452272402386626,
                    0.5101693931708503,
                    0.404949394786753,
                    0.15865985215878037
                ]
            },
            {
                "question_bleu": 0.7539221180326289,
                "options_bleu": [
                    0.3982591080485528,
                    0.12924952203832513,
                    0.1269262239735982,
                    0.20494695747544686
                ]
            },
            {
                "question_bleu": 0.733503637924837,
                "options_bleu": [
                    0.11823053204772466,
                    0.09709947527833854,
                    0.09083071358608567,
                    0.13101747895628205
                ]
            },
            {
                "question_bleu": 0.7192399680297693,
                "options_bleu": [
                    0.45292256856807694,
                    0.4428500142691474,
                    0.06970692565306981,
                    0.21850749656691937
                ]
            }
        ]
    },
    {
        "title": "Infinity according to Jorge Luis Borges - Ilan Stavans",
        "category": "Health",
        "questions-average-bleu": 0.7269865837490326,
        "options-average-bleu": 0.40753125976665505,
        "multiple-choice": [
            {
                "question_bleu": 0.7146704964214272,
                "options_bleu": [
                    0.40016016019225,
                    0.23953094040783438,
                    0.36177396082048563,
                    0.3521856535823236
                ]
            },
            {
                "question_bleu": 0.7952707287670506,
                "options_bleu": [
                    0.36980688472535445,
                    0.4081054713794032,
                    0.6042750794713536,
                    0.21769897651788855
                ]
            },
            {
                "question_bleu": 0.7381479309342973,
                "options_bleu": [
                    0.4519705738042162,
                    0.31239399369202553,
                    0.44437561917715573,
                    0.585956967450442
                ]
            },
            {
                "question_bleu": 0.67973698143584,
                "options_bleu": [
                    0.43138943204452074,
                    0.3627538269845734,
                    0.45886678012586496,
                    0.33913260910307497
                ]
            },
            {
                "question_bleu": 0.7071067811865476,
                "options_bleu": [
                    0.5321847348604716,
                    0.432014183039748,
                    0.5711077276020007,
                    0.274941620352113
                ]
            }
        ]
    },
    {
        "title": "Volcanic eruption explained - Steven Anderson",
        "category": "Science & Technology",
        "questions-average-bleu": 0.7006253175754793,
        "options-average-bleu": 0.17041109562457937,
        "multiple-choice": [
            {
                "question_bleu": 0.7031452428005499,
                "options_bleu": [
                    0.18788101322659978,
                    0.14721962637430702,
                    0.28271785501261626,
                    0.2179337309566676
                ]
            },
            {
                "question_bleu": 0.6535891896737434,
                "options_bleu": [
                    0.08136951578633313,
                    0.07774391736321141,
                    0.0979603890117761,
                    0.10081480846704004
                ]
            },
            {
                "question_bleu": 0.7409262050680517,
                "options_bleu": [
                    0.201466247515865,
                    0.14219639566069514,
                    0.2533105064914255,
                    0.335742588055335
                ]
            },
            {
                "question_bleu": 0.715008642007595,
                "options_bleu": [
                    0.047791993760422334,
                    0.08162326345844605,
                    0.2346360629901795,
                    0.059055988979644036
                ]
            },
            {
                "question_bleu": 0.6904573083274563,
                "options_bleu": [
                    0.18716334943986238,
                    0.20274936956943113,
                    0.28682359768707,
                    0.18202169268466023
                ]
            }
        ]
    },
    {
        "title": "The strange history of the world's most stolen painting - Noah Charney",
        "category": "Science & Technology",
        "questions-average-bleu": 0.7238652744656138,
        "options-average-bleu": 1.0,
        "multiple-choice": [
            {
                "question_bleu": 0.7541859578343534,
                "options_bleu": [
                    1.0,
                    1.0,
                    1.0,
                    1.0
                ]
            },
            {
                "question_bleu": 0.6981881395594116,
                "options_bleu": [
                    1.0,
                    1.0,
                    1.0,
                    1.0
                ]
            },
            {
                "question_bleu": 0.7191298999313552,
                "options_bleu": [
                    1.0,
                    1.0,
                    1.0,
                    1.0
                ]
            },
            {
                "question_bleu": 0.749634235443537,
                "options_bleu": [
                    1.0,
                    1.0,
                    1.0,
                    1.0
                ]
            },
            {
                "question_bleu": 0.6981881395594116,
                "options_bleu": [
                    1.0,
                    1.0,
                    1.0,
                    1.0
                ]
            }
        ]
    },
    {
        "title": "Why should you read \"The God of Small Things\" by Arundhati Roy? - Laura Wright",
        "category": "Literature",
        "questions-average-bleu": 0.7409435978455787,
        "options-average-bleu": 0.552172500782363,
        "multiple-choice": [
            {
                "question_bleu": 0.7264385742573204,
                "options_bleu": [
                    0.8010548969451144,
                    0.7598356856515925,
                    0.7825422900366437,
                    0.7598356856515925
                ]
            },
            {
                "question_bleu": 0.7419446627365011,
                "options_bleu": [
                    0.7952707287670506,
                    0.5773502691896257,
                    0.6000342906130847,
                    0.5200970009529277
                ]
            },
            {
                "question_bleu": 0.7364279629037999,
                "options_bleu": [
                    0.7186082239261684,
                    0.25224685587253176,
                    0.09062215589270772,
                    0.7172835948406505
                ]
            },
            {
                "question_bleu": 0.7755106492019573,
                "options_bleu": [
                    0.7825422900366437,
                    0.30878189539634476,
                    0.3324684441805843,
                    0.36330554542576643
                ]
            },
            {
                "question_bleu": 0.7243961401283154,
                "options_bleu": [
                    0.6147881529512643,
                    0.5015748226469445,
                    0.2279222207582525,
                    0.537284965911771
                ]
            }
        ]
    },
    {
        "title": "Performing brain surgery without a scalpel - Hyunsoo Joshua No",
        "category": "Design, Engineering & Technology",
        "questions-average-bleu": 0.6812088119602331,
        "options-average-bleu": 0.34488998823733225,
        "multiple-choice": [
            {
                "question_bleu": 0.6791653730973352,
                "options_bleu": [
                    0.016550047997254593,
                    0.16416452381081142,
                    0.2423861094838519,
                    0.0837197808083901
                ]
            },
            {
                "question_bleu": 0.6985342056580097,
                "options_bleu": [
                    0.23876116739439723,
                    0.3445497351376928,
                    0.17870473092164152,
                    0.21024692077841572
                ]
            },
            {
                "question_bleu": 0.716729493542774,
                "options_bleu": [
                    0.543568711108357,
                    0.5744582627799245,
                    0.1868030605525364,
                    0.2545286403887288
                ]
            },
            {
                "question_bleu": 0.6269199963292426,
                "options_bleu": [
                    0.5140755474474,
                    0.43980509235734633,
                    0.5921580141320887,
                    0.3558033135854104
                ]
            },
            {
                "question_bleu": 0.684694991173804,
                "options_bleu": [
                    0.535453062568715,
                    0.46860008630143446,
                    0.6828129079368713,
                    0.27065004925537595
                ]
            }
        ]
    },
    {
        "title": "How this disease changes the shape of your cells - Amber M. Yates",
        "category": "Health",
        "questions-average-bleu": 0.7267930460436066,
        "options-average-bleu": 0.5839853637550172,
        "multiple-choice": [
            {
                "question_bleu": 0.747060787803606,
                "options_bleu": [
                    0.42908614936824124,
                    0.5345224838248488,
                    0.44573518321953964,
                    0.4709207802660356
                ]
            },
            {
                "question_bleu": 0.7633947323726819,
                "options_bleu": [
                    0.6606328636027614,
                    0.6964705665515708,
                    0.6076795808137692,
                    0.4381129694353713
                ]
            },
            {
                "question_bleu": 0.7118368561050571,
                "options_bleu": [
                    0.7765453555044466,
                    0.6500593260343692,
                    0.7765453555044466,
                    0.6904573083274563
                ]
            },
            {
                "question_bleu": 0.7192399680297693,
                "options_bleu": [
                    0.7765453555044466,
                    0.6865890479690392,
                    0.6828267746069693,
                    0.4949232003839765
                ]
            },
            {
                "question_bleu": 0.6924328859069189,
                "options_bleu": [
                    0.4728708045015879,
                    0.40546144983876986,
                    0.5695988432761473,
                    0.41412387656655203
                ]
            }
        ]
    },
    {
        "title": "The counting by fives song | Counting songs",
        "category": "Numbers & Operations",
        "questions-average-bleu": 0.7260287005828306,
        "options-average-bleu": 0.3120828355198233,
        "multiple-choice": [
            {
                "question_bleu": 0.7047997136316118,
                "options_bleu": [
                    0.645777692487244,
                    0.5266403878479265,
                    0.5695988432761473,
                    0.23095037282123296
                ]
            },
            {
                "question_bleu": 0.7352923728444684,
                "options_bleu": [
                    0.36787944117144233,
                    0.5475182535069453,
                    0.6065306597126334,
                    0.36787944117144233
                ]
            },
            {
                "question_bleu": 0.6959325433099479,
                "options_bleu": [
                    0.11380295453101374,
                    0.1353352832366127,
                    0.1353352832366127,
                    0.1353352832366127
                ]
            },
            {
                "question_bleu": 0.7755106492019573,
                "options_bleu": [
                    0.11380295453101374,
                    0.1353352832366127,
                    0.1353352832366127,
                    0.27952792741962756
                ]
            },
            {
                "question_bleu": 0.7186082239261684,
                "options_bleu": [
                    0.28574404296988,
                    0.5828233954152654,
                    0.0661074021019606,
                    0.2603965252496297
                ]
            }
        ]
    },
    {
        "title": "Why do we have leap years?",
        "category": "Teaching & Education",
        "questions-average-bleu": 0,
        "options-average-bleu": 0,
        "multiple-choice": []
    },
    {
        "title": "Is binge watching bad for you?",
        "category": "Health",
        "questions-average-bleu": 0.6634357752282348,
        "options-average-bleu": 0.651586527867214,
        "multiple-choice": [
            {
                "question_bleu": 0.6831645569386161,
                "options_bleu": [
                    0.4322513758218357,
                    0.17388520875116095,
                    0.3984049338436474,
                    0.06440906420111579
                ]
            },
            {
                "question_bleu": 0.6893409630302637,
                "options_bleu": [
                    0.721924843310955,
                    0.39626338862382493,
                    0.4338507394036409,
                    0.4506022621318761
                ]
            },
            {
                "question_bleu": 0.6536410556575404,
                "options_bleu": [
                    1.0,
                    1.0,
                    1.0,
                    1.0
                ]
            },
            {
                "question_bleu": 0.6544867736464346,
                "options_bleu": [
                    0.48578114576020687,
                    0.4611514122385435,
                    0.5321847348604716,
                    0.481021448397001
                ]
            },
            {
                "question_bleu": 0.6365455268683196,
                "options_bleu": [
                    1.0,
                    1.0,
                    1.0,
                    1.0
                ]
            }
        ]
    },
    {
        "title": "Meet the microscopic life in your home--- and on your face - Anne Madden",
        "category": "Design, Engineering & Technology",
        "questions-average-bleu": 0.7151310806324715,
        "options-average-bleu": 0.8430412752933905,
        "multiple-choice": [
            {
                "question_bleu": 0.6989307622784944,
                "options_bleu": [
                    0.5555238068023582,
                    0.5993418090318328,
                    0.6389431042462724,
                    0.8408964152537145
                ]
            },
            {
                "question_bleu": 0.724724590060866,
                "options_bleu": [
                    1.0,
                    1.0,
                    1.0,
                    1.0
                ]
            },
            {
                "question_bleu": 0.7389984311706962,
                "options_bleu": [
                    1.0,
                    1.0,
                    1.0,
                    1.0
                ]
            },
            {
                "question_bleu": 0.7217950347929304,
                "options_bleu": [
                    1.0,
                    1.0,
                    1.0,
                    1.0
                ]
            },
            {
                "question_bleu": 0.6912065848593708,
                "options_bleu": [
                    0.5418580162342823,
                    0.5019724248795792,
                    0.6111822018177674,
                    0.5711077276020007
                ]
            }
        ]
    },
    {
        "title": "Why do we wrinkle when wet?",
        "category": "Health",
        "questions-average-bleu": 0.6946621302046239,
        "options-average-bleu": 0.3293065409755852,
        "multiple-choice": [
            {
                "question_bleu": 0.7745966692414834,
                "options_bleu": [
                    0.38163309113713373,
                    0.42257712736425823,
                    0.30645129942076654,
                    0.37333473646530985
                ]
            },
            {
                "question_bleu": 0.6865890479690392,
                "options_bleu": [
                    0.3914102142227981,
                    0.4518010018049224,
                    0.46099008584959905,
                    0.8091067115702212
                ]
            },
            {
                "question_bleu": 0.6251943537695185,
                "options_bleu": [
                    0.0024787521766663585,
                    0.025561533206507392,
                    0.025561533206507392,
                    0.025561533206507392
                ]
            },
            {
                "question_bleu": 0.7071067811865476,
                "options_bleu": [
                    0.29779515294014014,
                    0.3650548038541865,
                    0.4469159490152934,
                    0.3664308104982354
                ]
            },
            {
                "question_bleu": 0.6798237988565304,
                "options_bleu": [
                    0.338199926733156,
                    0.41509845622052555,
                    0.2139786312919189,
                    0.46618946932704897
                ]
            }
        ]
    },
    {
        "title": "3D shapes song | Shapes for kids",
        "category": "Geometry",
        "questions-average-bleu": 0.7583735775680385,
        "options-average-bleu": 0.8598909691413702,
        "multiple-choice": [
            {
                "question_bleu": 0.7707713836060629,
                "options_bleu": [
                    1.0,
                    0.6389431042462724,
                    0.8891397050194614,
                    0.7071067811865476
                ]
            },
            {
                "question_bleu": 0.7098962112020106,
                "options_bleu": [
                    0.6337834876616586,
                    0.7825422900366437,
                    0.7875110621102679,
                    0.816496580927726
                ]
            },
            {
                "question_bleu": 0.7559289460184544,
                "options_bleu": [
                    0.7071067811865476,
                    0.6389431042462724,
                    0.7071067811865476,
                    0.8891397050194614
                ]
            },
            {
                "question_bleu": 0.785629301801026,
                "options_bleu": [
                    1.0,
                    1.0,
                    1.0,
                    1.0
                ]
            },
            {
                "question_bleu": 0.769642045212638,
                "options_bleu": [
                    1.0,
                    1.0,
                    1.0,
                    1.0
                ]
            }
        ]
    },
    {
        "title": "The most common STI in the world - Emma Bryce",
        "category": "Literature & Language",
        "questions-average-bleu": 0.7333326819555747,
        "options-average-bleu": 0.43019696240318916,
        "multiple-choice": [
            {
                "question_bleu": 0.7632053278841269,
                "options_bleu": [
                    0.2519921893632723,
                    0.2502447384232383,
                    0.20520135490129188,
                    0.24435249825334956
                ]
            },
            {
                "question_bleu": 0.8074157792118413,
                "options_bleu": [
                    0.6622152291011697,
                    0.2943567124284288,
                    0.1382109806372432,
                    0.32253883071974426
                ]
            },
            {
                "question_bleu": 0.6778409044431745,
                "options_bleu": [
                    0.44815017360408727,
                    0.06623699576124968,
                    0.5019724248795792,
                    0.4105483718343193
                ]
            },
            {
                "question_bleu": 0.7002959704822554,
                "options_bleu": [
                    0.5454853089396473,
                    0.7994599581938531,
                    0.31880105948138787,
                    0.8233506773785282
                ]
            },
            {
                "question_bleu": 0.7179054277564751,
                "options_bleu": [
                    0.6622152291011697,
                    0.33980884896942454,
                    0.6116908849062525,
                    0.7071067811865476
                ]
            }
        ]
    },
    {
        "title": "Who was the world's first author? - Soraya Field Fiorio",
        "category": "Literature & Language",
        "questions-average-bleu": 0.749734878924504,
        "options-average-bleu": 0.3889504572344986,
        "multiple-choice": [
            {
                "question_bleu": 0.7111824933579799,
                "options_bleu": [
                    0.2726150787505473,
                    0.25234374955543365,
                    0.25678168744651036,
                    0.32909043858294346
                ]
            },
            {
                "question_bleu": 0.8178362024635121,
                "options_bleu": [
                    0.2263059965817483,
                    0.35930411196308426,
                    0.36539221045150677,
                    0.27272035432845076
                ]
            },
            {
                "question_bleu": 0.7234804230870479,
                "options_bleu": [
                    0.41412387656655203,
                    0.38824116850645757,
                    0.370559451116619,
                    0.3877888479306005
                ]
            },
            {
                "question_bleu": 0.7298723202748774,
                "options_bleu": [
                    0.7663029554391028,
                    0.7400828044922853,
                    0.42728700639623407,
                    0.3592209878136327
                ]
            },
            {
                "question_bleu": 0.7663029554391028,
                "options_bleu": [
                    0.35286620874339625,
                    0.4099190286914736,
                    0.4061953197187379,
                    0.42186786161465595
                ]
            }
        ]
    },
    {
        "title": "Harvey Milk's radical vision of equality - Lillian Faderman",
        "category": "Social Studies",
        "questions-average-bleu": 0.7303923342798206,
        "options-average-bleu": 1.0,
        "multiple-choice": [
            {
                "question_bleu": 0.7598356856515925,
                "options_bleu": [
                    1.0,
                    1.0,
                    1.0,
                    1.0
                ]
            },
            {
                "question_bleu": 0.7419446627365011,
                "options_bleu": [
                    1.0,
                    1.0,
                    1.0,
                    1.0
                ]
            },
            {
                "question_bleu": 0.7453559924999299,
                "options_bleu": [
                    1.0,
                    1.0,
                    1.0,
                    1.0
                ]
            },
            {
                "question_bleu": 0.6702688642160264,
                "options_bleu": [
                    1.0,
                    1.0,
                    1.0,
                    1.0
                ]
            },
            {
                "question_bleu": 0.7345564662950537,
                "options_bleu": [
                    1.0,
                    1.0,
                    1.0,
                    1.0
                ]
            }
        ]
    },
    {
        "title": "Is human evolution speeding up or slowing down? - Laurence Hurst",
        "category": "Science & Technology",
        "questions-average-bleu": 0.7185626533288781,
        "options-average-bleu": 0.9239359002367937,
        "multiple-choice": [
            {
                "question_bleu": 0.7115965735877551,
                "options_bleu": [
                    0.8316033157750904,
                    0.2746478265715413,
                    0.5442191092561398,
                    0.8282477531331041
                ]
            },
            {
                "question_bleu": 0.8408964152537145,
                "options_bleu": [
                    1.0,
                    1.0,
                    1.0,
                    1.0
                ]
            },
            {
                "question_bleu": 0.6516519700462822,
                "options_bleu": [
                    1.0,
                    1.0,
                    1.0,
                    1.0
                ]
            },
            {
                "question_bleu": 0.7391605811379237,
                "options_bleu": [
                    1.0,
                    1.0,
                    1.0,
                    1.0
                ]
            },
            {
                "question_bleu": 0.6495077266187151,
                "options_bleu": [
                    1.0,
                    1.0,
                    1.0,
                    1.0
                ]
            }
        ]
    },
    {
        "title": "The surprising similarities between Twister and intelligence",
        "category": "Health",
        "questions-average-bleu": 0.6870541106118209,
        "options-average-bleu": 0.5433913236217401,
        "multiple-choice": [
            {
                "question_bleu": 0.6569591371638285,
                "options_bleu": [
                    0.3521856535823236,
                    0.3161487584488943,
                    0.36260298748796105,
                    0.38163309113713373
                ]
            },
            {
                "question_bleu": 0.6803749333171202,
                "options_bleu": [
                    0.360878186189822,
                    0.32946178962946737,
                    0.4428500142691474,
                    0.30066081045110243
                ]
            },
            {
                "question_bleu": 0.7071067811865476,
                "options_bleu": [
                    0.8035841561222477,
                    0.5946035575013605,
                    0.7479003751434347,
                    0.6580370064762462
                ]
            },
            {
                "question_bleu": 0.6912065848593708,
                "options_bleu": [
                    0.7598356856515925,
                    0.7447819789879647,
                    0.463502386414385,
                    0.8055344092731546
                ]
            },
            {
                "question_bleu": 0.6996231165322373,
                "options_bleu": [
                    0.4128074884933345,
                    1.0,
                    0.4630777161991027,
                    0.567740420976129
                ]
            }
        ]
    },
    {
        "title": "Where will you be able to live in 20 years? - Carol Farbotko and Ingrid Boas",
        "category": "Science & Technology",
        "questions-average-bleu": 0.676296899724676,
        "options-average-bleu": 0.2942402517032091,
        "multiple-choice": [
            {
                "question_bleu": 0.6280169733958691,
                "options_bleu": [
                    0.08811850850050418,
                    0.43645382979233377,
                    0.45869664086091444,
                    0.11413281991486751
                ]
            },
            {
                "question_bleu": 0.6912065848593708,
                "options_bleu": [
                    0.3311644912364497,
                    0.34326274481047087,
                    0.07361023855081494,
                    0.1383941445793565
                ]
            },
            {
                "question_bleu": 0.721023747812814,
                "options_bleu": [
                    0.4027672046365773,
                    0.5236421927181384,
                    0.3627538269845734,
                    0.4005274484725572
                ]
            },
            {
                "question_bleu": 0.6759709806875497,
                "options_bleu": [
                    0.41731572734660466,
                    0.32630496621343463,
                    0.37494051432044967,
                    0.38988804989373166
                ]
            },
            {
                "question_bleu": 0.665266211867776,
                "options_bleu": [
                    0.13972680638271986,
                    0.07675926921556564,
                    0.11785714869126361,
                    0.3684884609428539
                ]
            }
        ]
    },
    {
        "title": "Why beavers are the smartest thing in fur pants",
        "category": "Science & Technology",
        "questions-average-bleu": 0.735376034389404,
        "options-average-bleu": 0.46966845491595743,
        "multiple-choice": [
            {
                "question_bleu": 0.7903765226488096,
                "options_bleu": [
                    0.43157014485767914,
                    0.6147881529512643,
                    0.23101429614281777,
                    0.4096358374836476
                ]
            },
            {
                "question_bleu": 0.8047211478535489,
                "options_bleu": [
                    0.3386854985606571,
                    0.43449285147738775,
                    0.378448113759187,
                    0.46674159385179825
                ]
            },
            {
                "question_bleu": 0.6959325433099479,
                "options_bleu": [
                    0.5207332064246721,
                    0.6950150297221263,
                    0.36739131889547183,
                    0.40546144983876986
                ]
            },
            {
                "question_bleu": 0.6707217794445165,
                "options_bleu": [
                    0.3258816484718314,
                    0.40383414697541437,
                    0.24419063932094665,
                    0.4598700064781044
                ]
            },
            {
                "question_bleu": 0.7151281786901973,
                "options_bleu": [
                    0.6865890479690392,
                    0.7226568811456053,
                    0.6904573083274563,
                    0.5659119256652702
                ]
            }
        ]
    },
    {
        "title": "Why we should draw more (and photograph less)",
        "category": "Physical Fitness",
        "questions-average-bleu": 0.7071330705702499,
        "options-average-bleu": 0.308522225619828,
        "multiple-choice": [
            {
                "question_bleu": 0.7387670965262431,
                "options_bleu": [
                    0.3735942070746957,
                    0.210821402663361,
                    0.3038995785073711,
                    0.29782360515973005
                ]
            },
            {
                "question_bleu": 0.6831645569386161,
                "options_bleu": [
                    0.28180187040026855,
                    0.7053418620664446,
                    0.4306919529130621,
                    0.27233170963734965
                ]
            },
            {
                "question_bleu": 0.7384102902900735,
                "options_bleu": [
                    0.28003939441255277,
                    0.25645640348871285,
                    0.48024244086421736,
                    0.3971847853433439
                ]
            },
            {
                "question_bleu": 0.6904573083274563,
                "options_bleu": [
                    0.2544766798592505,
                    0.30340683042754474,
                    0.20113007032295432,
                    0.6011405346781413
                ]
            },
            {
                "question_bleu": 0.6848661007688605,
                "options_bleu": [
                    0.11380295453101374,
                    0.2635921827002181,
                    0.07133302367316396,
                    0.07133302367316396
                ]
            }
        ]
    },
    {
        "title": "The history of manners",
        "category": "Psychology",
        "questions-average-bleu": 0.6794663814307853,
        "options-average-bleu": 0.3778510697171481,
        "multiple-choice": [
            {
                "question_bleu": 0.7009305846091448,
                "options_bleu": [
                    0.4096782538277298,
                    0.4653024295510498,
                    0.4974292207467277,
                    0.463502386414385
                ]
            },
            {
                "question_bleu": 0.6363082311973168,
                "options_bleu": [
                    0.5336172773868456,
                    0.2390457218668787,
                    0.22793076437070336,
                    0.48056228282695085
                ]
            },
            {
                "question_bleu": 0.6908938923636813,
                "options_bleu": [
                    0.5623413251903491,
                    0.19518444069129323,
                    0.24078435074822624,
                    0.476895599763377
                ]
            },
            {
                "question_bleu": 0.6836102833823653,
                "options_bleu": [
                    0.4709207802660356,
                    0.4653024295510498,
                    0.1708738075999045,
                    0.42379865741502165
                ]
            },
            {
                "question_bleu": 0.6855889156014183,
                "options_bleu": [
                    0.4188216850419828,
                    0.161692143534558,
                    0.18983545113550931,
                    0.463502386414385
                ]
            }
        ]
    },
    {
        "title": "Can you solve the multiplying rabbits riddle? - Alex Gendler",
        "category": "Mathematics",
        "questions-average-bleu": 0.7118307075717254,
        "options-average-bleu": 1.0,
        "multiple-choice": [
            {
                "question_bleu": 0.7009305846091448,
                "options_bleu": [
                    1.0,
                    1.0,
                    1.0,
                    1.0
                ]
            },
            {
                "question_bleu": 0.7598356856515925,
                "options_bleu": [
                    1.0,
                    1.0,
                    1.0,
                    1.0
                ]
            },
            {
                "question_bleu": 0.665266211867776,
                "options_bleu": [
                    1.0,
                    1.0,
                    1.0,
                    1.0
                ]
            },
            {
                "question_bleu": 0.7326545101601926,
                "options_bleu": [
                    1.0,
                    1.0,
                    1.0,
                    1.0
                ]
            },
            {
                "question_bleu": 0.7004665455699209,
                "options_bleu": [
                    1.0,
                    1.0,
                    1.0,
                    1.0
                ]
            }
        ]
    },
    {
        "title": "Art with Mati and Dada \u2013 Henri Matisse",
        "category": "Visual Arts",
        "questions-average-bleu": 0.7282659149517323,
        "options-average-bleu": 0.5014209412176089,
        "multiple-choice": [
            {
                "question_bleu": 0.6887246539984299,
                "options_bleu": [
                    0.6147881529512643,
                    0.6042750794713536,
                    0.6042750794713536,
                    0.48217764100758403
                ]
            },
            {
                "question_bleu": 0.7025297977970931,
                "options_bleu": [
                    0.4518010018049224,
                    0.16963998099931427,
                    0.40016016019225,
                    0.4261082723917018
                ]
            },
            {
                "question_bleu": 0.6985342056580097,
                "options_bleu": [
                    0.4811042931139691,
                    0.2478833847613446,
                    0.3168900267453786,
                    0.17278330851481746
                ]
            },
            {
                "question_bleu": 0.8125424861344327,
                "options_bleu": [
                    0.5026386140359251,
                    0.5109955811291784,
                    0.4949232003839765,
                    0.5839496294503805
                ]
            },
            {
                "question_bleu": 0.7389984311706962,
                "options_bleu": [
                    0.6529942057256104,
                    0.6529942057256104,
                    1.0,
                    0.6580370064762462
                ]
            }
        ]
    },
    {
        "title": "Why don't haircuts hurt?",
        "category": "Science & Technology",
        "questions-average-bleu": 0.7388671747371339,
        "options-average-bleu": 0.018037078034406552,
        "multiple-choice": [
            {
                "question_bleu": 0.69707435607959,
                "options_bleu": [
                    0.019978928794728276,
                    0.026615141179810137,
                    0.030458964430383362,
                    0.011362661607087033
                ]
            },
            {
                "question_bleu": 0.7400828044922853,
                "options_bleu": [
                    0.0007932508104543667,
                    0.025492937571784436,
                    0.008537416741700098,
                    0.009512635740973741
                ]
            },
            {
                "question_bleu": 0.710084138739636,
                "options_bleu": [
                    4.607185863474797e-06,
                    0.0025196009827343066,
                    0.00041102920424132214,
                    0.00026201198040977044
                ]
            },
            {
                "question_bleu": 0.8254605646966103,
                "options_bleu": [
                    0.020639184722776004,
                    0.049639232274333665,
                    0.07000403095754891,
                    0.05116235677227602
                ]
            },
            {
                "question_bleu": 0.721634009677548,
                "options_bleu": [
                    0.011683887090085703,
                    0.009545635144619112,
                    0.009403344385353276,
                    0.0027147031109680027
                ]
            }
        ]
    }
]